texttools/__init__.py
texttools/base/__init__.py
texttools/base/base_categorizer.py
texttools/base/base_keyword_extractor.py
texttools/base/base_ner_extractor.py
texttools/base/base_question_detector.py
texttools/base/base_question_generator.py
texttools/base/base_question_merger.py
texttools/base/base_question_rewriter.py
texttools/base/base_router.py
texttools/base/base_summarizer.py
texttools/base/base_task_performer.py
texttools/base/base_translator.py
texttools/batch_manager/__init__.py
texttools/batch_manager/batch_manager.py
texttools/batch_manager/batch_runner.py
texttools/formatter/__init__.py
texttools/formatter/base.py
texttools/formatter/gemma3_formatter.py
texttools/handlers/__init__.py
texttools/handlers/handlers.py
texttools/handlers/categorizer/__init__.py
texttools/handlers/categorizer/categorizer.py
texttools/tools/__init__.py
texttools/tools/categorizer/__init__.py
texttools/tools/categorizer/encoder_model/__init__.py
texttools/tools/categorizer/encoder_model/encoder_vectorizer.py
texttools/tools/categorizer/llm/__init__.py
texttools/tools/categorizer/llm/gemma_categorizer.py
texttools/tools/categorizer/llm/openai_categorizer.py
texttools/tools/keyword_extractor/__init__.py
texttools/tools/keyword_extractor/gemma_extractor.py
texttools/tools/merger/__init__.py
texttools/tools/merger/gemma_question_merger.py
texttools/tools/ner/__init__.py
texttools/tools/ner/gemma_ner_extractor.py
texttools/tools/question_detector/__init__.py
texttools/tools/question_detector/gemma_detector.py
texttools/tools/question_detector/llm_detector.py
texttools/tools/question_generator/__init__.py
texttools/tools/question_generator/gemma_question_generator.py
texttools/tools/reranker/__init__.py
texttools/tools/reranker/reranker.py
texttools/tools/reranker/scorer.py
texttools/tools/reranker/sorter.py
texttools/tools/rewriter/__init__.py
texttools/tools/rewriter/gemma_question_rewriter.py
texttools/tools/router/__init__.py
texttools/tools/router/gemma_router.py
hamta_texttools-0.1.43.dist-info/METADATA
hamta_texttools-0.1.43.dist-info/WHEEL
hamta_texttools-0.1.43.dist-info/top_level.txt
hamta_texttools-0.1.43.dist-info/RECORD
