Metadata-Version: 2.4
Name: hamta-texttools
Version: 0.1.43
Summary: A set of high-level NLP tools
Author: Tohidi, Montazer, Givechi, mousavinezhad
Requires-Python: >=3.8
Requires-Dist: openai==1.97.1
Requires-Dist: numpy==1.26.4
